LICENSE
Makefile
README.md
changelog.md
gcodereader/__init__.py
gcodereader/gcodereader.py
gcodereader/interpreter.py
gcodereader/meshWriter.py
gcodereader/reader.py
gcodereader/support.py
gcodereader/writer.py
gcodereader-0.4.5.dist-info/LICENSE
gcodereader-0.4.5.dist-info/METADATA
gcodereader-0.4.5.dist-info/WHEEL
gcodereader-0.4.5.dist-info/entry_points.txt
gcodereader-0.4.5.dist-info/RECORD
