Metadata-Version: 2.1
Name: gcodereader
Version: 0.4.5
Summary: Read gcode and translate into peridigm input
Home-page: https://gitlab.dlr.de/fa_sw/peridynamik/gcodereader
License: BSD license
Keywords: gcode,peridigm,translator
Author: Jan-Timo Hesse
Requires-Python: >=3.8,<4.0
Classifier: License :: Other/Proprietary License
Classifier: Programming Language :: Python :: 3
Classifier: Programming Language :: Python :: 3.8
Classifier: Programming Language :: Python :: 3.9
Classifier: Programming Language :: Python :: 3.10
Classifier: Programming Language :: Python :: 3.11
Requires-Dist: matplotlib
Requires-Dist: numpy
Requires-Dist: rich
Requires-Dist: scikit-learn
Requires-Dist: tomlkit
Project-URL: Repository, https://gitlab.dlr.de/fa_sw/peridynamik/gcodereader
